silvr_client/__init__.py
silvr_client/authentication.py
silvr_client/choices.py
silvr_client/client.py
silvr_client/models.py
silvr_client/tests/__init__.py
silvr_client-0.1.1.dist-info/LICENCE
silvr_client-0.1.1.dist-info/METADATA
silvr_client-0.1.1.dist-info/WHEEL
silvr_client-0.1.1.dist-info/top_level.txt
silvr_client-0.1.1.dist-info/RECORD
